testing_providers/__init__.py
testing_providers/mqtt.py
testing_providers/tcp.py
testing_providers/ws.py
testing_providers-0.1.1a3.dist-info/WHEEL
testing_providers-0.1.1a3.dist-info/METADATA
testing_providers-0.1.1a3.dist-info/RECORD
